torchlit/__init__.py
torchlit/data/__init__.py
torchlit/data/datasets.py
torchlit/data/scraper.py
torchlit/models/__init__.py
torchlit/models/model.py
torchlit/utils/__init__.py
torchlit-0.1.4.dist-info/LICENSE
torchlit-0.1.4.dist-info/METADATA
torchlit-0.1.4.dist-info/WHEEL
torchlit-0.1.4.dist-info/top_level.txt
torchlit-0.1.4.dist-info/RECORD
