Metadata-Version: 2.1
Name: torchlit
Version: 0.1.4
Summary: torchlit - thin wrappers for Pytorch
Home-page: https://github.com/himanshu-dutta/torchlit
Author: Himanshu Dutta
Author-email: meet.himanshu.dutta@gmail.com
License: MIT License
Platform: linux
Platform: unix
Requires-Python: >3.5.2
Requires-Dist: torch (>=1.6.0)
